timeit2/__init__.py
timeit2-1.0.0.dist-info/WHEEL
timeit2-1.0.0.dist-info/METADATA
timeit2-1.0.0.dist-info/RECORD
